imap_codec-0.1.0.dist-info/METADATA
imap_codec-0.1.0.dist-info/WHEEL
imap_codec/__init__.py
imap_codec/__init__.pyi
imap_codec/py.typed
imap_codec/imap_codec.cpython-39-i386-linux-gnu.so
imap_codec-0.1.0.dist-info/RECORD
