Metadata-Version: 2.3
Name: imap-codec
Version: 0.1.0
Classifier: License :: OSI Approved :: Apache Software License
Classifier: License :: OSI Approved :: MIT License
Classifier: Natural Language :: English
Classifier: Operating System :: MacOS :: MacOS X
Classifier: Operating System :: Microsoft :: Windows
Classifier: Operating System :: POSIX :: Linux
Classifier: Programming Language :: Rust
Classifier: Programming Language :: Python :: Implementation :: CPython
Classifier: Programming Language :: Python :: Implementation :: PyPy
Classifier: Topic :: Communications :: Email :: Post-Office :: IMAP
Classifier: Topic :: Software Development :: Libraries
Classifier: Typing :: Typed
Summary: Python bindings for imap-codec Rust crate
Keywords: email,imap,codec,parser
Author: Damian Poddebniak <poddebniak@mailbox.org>, Henning Holm <git@henningholm.de>
Author-email: Damian Poddebniak <poddebniak@mailbox.org>, Henning Holm <git@henningholm.de>
License: MIT OR Apache-2.0
Requires-Python: >=3.8
Project-URL: source, https://github.com/duesee/imap-codec
Project-URL: tracker, https://github.com/duesee/imap-codec/issues
